{"https://www.oschina.net/":1283,"https://www.baidu.com/s?ie=UTF-8&wd=hello":1170,"https://cn.bing.com/search?q=hello":1121,"https://www.bilibili.com/":10528,"https://www.csdn.net/":1191,"https://www.google.com/search?q=hello":1741,"https://github.com/":1689,"https://pwa.clicli.me/":-1,"https://www.youtube.com/":15866,"https://segmentfault.com/":2450,"https://www.cnblogs.com/":904,"https://juejin.im/":1668,"https://www.jianshu.com/":484,"https://stackoverflow.com/":838,"https://www.baidu.com":255,"https://www.google.com":211,"https://cn.bing.com":212,"https://www.douban.com/":1309,"https://en.wikipedia.org/wiki/Main_Page":1035,"https://www.facebook.com/":320,"https://twitter.com/":236,"https://www.amazon.com/":3555,"https://play.google.com/store":10869,"https://www.netflix.com/jp-en/":254,"https://www.yahoo.com/":6518,"http://daily.zhihu.com/":241,"https://www.sina.com.cn/":4743,"https://www.toutiao.com/":347}
