{"https://www.oschina.net/":1298,"https://www.baidu.com/s?ie=UTF-8&wd=hello":1178,"https://cn.bing.com/search?q=hello":1106,"https://www.bilibili.com/":10405,"https://www.csdn.net/":2991,"https://www.google.com/search?q=hello":1933,"https://github.com/":1689,"https://pwa.clicli.me/":-1,"https://www.youtube.com/":16162,"https://segmentfault.com/":2476,"https://www.cnblogs.com/":905,"https://juejin.im/":4540,"https://www.jianshu.com/":484,"https://stackoverflow.com/":845,"https://www.baidu.com":259,"https://www.google.com":182,"https://cn.bing.com":216,"https://www.douban.com/":1094,"https://en.wikipedia.org/wiki/Main_Page":1025,"https://www.facebook.com/":320,"https://twitter.com/":236,"https://www.amazon.com/":2229,"https://play.google.com/store":10975,"https://www.netflix.com/jp-en/":254,"https://www.yahoo.com/":8004,"http://daily.zhihu.com/":241,"https://www.sina.com.cn/":-1,"https://www.toutiao.com/":347}
