{"https://www.oschina.net/":1996,"https://www.baidu.com/s?ie=UTF-8&wd=hello":1108,"https://cn.bing.com/search?q=hello":1007,"https://www.bilibili.com/":10971,"https://www.csdn.net/":3409,"https://www.google.com/search?q=hello":3431,"https://github.com/":1366,"https://pwa.clicli.me/":-1,"https://www.youtube.com/":18069,"https://segmentfault.com/":1835,"https://www.cnblogs.com/":942,"https://juejin.im/":4446,"https://www.jianshu.com/":503,"https://stackoverflow.com/":866,"https://www.baidu.com":262,"https://www.google.com":180,"https://cn.bing.com":217,"https://www.douban.com/":1304,"https://en.wikipedia.org/wiki/Main_Page":993,"https://www.facebook.com/":286,"https://twitter.com/":192,"https://www.amazon.com/":2492,"https://play.google.com/store":11567,"https://www.netflix.com/jp-en/":516,"https://www.yahoo.com/":7350,"http://daily.zhihu.com/":241,"https://www.sina.com.cn/":4885,"https://www.toutiao.com/":328}
