{"https://www.oschina.net/":1983,"https://www.baidu.com/s?ie=UTF-8&wd=hello":1067,"https://cn.bing.com/search?q=hello":1000,"https://www.bilibili.com/":12106,"https://www.csdn.net/":2627,"https://www.google.com/search?q=hello":2106,"https://github.com/":1441,"https://pwa.clicli.me/":-1,"https://www.youtube.com/":24916,"https://segmentfault.com/":592,"https://www.cnblogs.com/":1107,"https://juejin.im/":2637,"https://www.jianshu.com/":517,"https://stackoverflow.com/":1210,"https://www.baidu.com":304,"https://www.google.com":196,"https://cn.bing.com":282,"https://www.douban.com/":1266,"https://en.wikipedia.org/wiki/Main_Page":1106,"https://www.facebook.com/":253,"https://twitter.com/":220,"https://www.amazon.com/":3463,"https://play.google.com/store":9875,"https://www.netflix.com/jp-en/":536,"https://www.yahoo.com/":6239,"http://daily.zhihu.com/":256,"https://www.sina.com.cn/":4858,"https://www.toutiao.com/":1470}
