{"https://www.oschina.net/":1985,"https://www.baidu.com/s?ie=UTF-8&wd=hello":1162,"https://cn.bing.com/search?q=hello":1028,"https://www.bilibili.com/":17609,"https://www.csdn.net/":3454,"https://www.google.com/search?q=hello":2194,"https://github.com/":1489,"https://pwa.clicli.me/":-1,"https://www.youtube.com/":24823,"https://segmentfault.com/":575,"https://www.cnblogs.com/":1115,"https://juejin.im/":3474,"https://www.jianshu.com/":708,"https://stackoverflow.com/":973,"https://www.baidu.com":314,"https://www.google.com":200,"https://cn.bing.com":319,"https://www.douban.com/":1384,"https://en.wikipedia.org/wiki/Main_Page":1102,"https://www.facebook.com/":257,"https://twitter.com/":242,"https://www.amazon.com/":2889,"https://play.google.com/store":10552,"https://www.netflix.com/jp-en/":516,"https://www.yahoo.com/":6478,"http://daily.zhihu.com/":243,"https://www.sina.com.cn/":4776,"https://www.toutiao.com/":1894,"https://pornhub.com/":3112,"https://my.oschina.net/ahaoboy":2828,"https://www.reddit.com/":6143,"https://yahoo.com/":6183,"https://juejin.cn/":2383}
